{
  "Homme": {
    "description": "",
    "info": {
      "health": 20,
      "mana": 10,
      "energy": 20,
      "stats": {
        "attack": 3,
        "defence": 3,
        "speed": 0.15,
        "critic": 0.2
      },
      "perks": {
        "forge": {
          "level": 2,
          "bonus": 1.25,
          "xp": 0
        },
        "chasse": {
          "level": 2,
          "bonus": 1.25,
          "xp": 0
        },
        "minage": {
          "level": 2,
          "bonus": 1.25,
          "xp": 0
        }
      }
    }
  },
  "Homme-loup": {
    "description": "",
    "info": {
      "health": 20,
      "mana": 15,
      "energy": 20,
      "stats": {
        "attack": 3,
        "defence": 3,
        "speed": 0.2,
        "critic": 0.15
      },
      "perks": {
        "forge": {
          "level": 3,
          "bonus": 1.25,
          "xp": 0
        },
        "combat": {
          "level": 2,
          "xp": 0,
          "bonus": 1.25
        }
      }
    }
  },
  "Homme-chat": {
    "description": "",
    "info": {
      "health": 20,
      "mana": 20,
      "energy": 15,
      "stats": {
        "attack": 2,
        "defence": 2,
        "speed": 0.4,
        "critic": 0.2
      },
      "perks": {
        "chasse": {
          "level": 3,
          "bonus": 1.5,
          "xp": 0
        },
        "vol": {
          "level": 2,
          "bonus": 1.5,
          "xp": 0
        },
        "assassin": {
          "level": 2,
          "bonus": 1.5,
          "xp": 0
        }
      }
    }
  },
  "elfe": {
    "description": "",
    "info": {
      "health": 20,
      "mana": 35,
      "energy": 20,
      "perks": {
        "forge": {
          "level": 5,
          "bonus": 1.25,
          "xp": 0
        },
        "parade": {
          "level": 2,
          "xp": 0,
          "bonus": 1.3
        },
        "enchantement": {
          "level": 2,
          "xp": 0,
          "bonus": 1.25
        }
      },
      "stats": {
        "attack": 3,
        "defence": 3,
        "speed": 0.2,
        "critic": 0.20
      }
    }
  },
  "elfe-noir": {
    "description": "",
    "info": {
      "health": 20,
      "mana": 30,
      "energy": 20,
      "perks": {
        "forge": {
          "level": 3,
          "bonus": 1.3,
          "xp": 0
        },
        "enchantement": {
          "level": 3,
          "bonus": 1.25,
          "xp": 0
        }
      },
      "stats": {
        "attack": 3,
        "defence": 3,
        "speed": 0.2,
        "critic": 0.20
      }
    }
  },
  "orc": {
    "description": "",
    "info": {
      "health": 30,
      "mana": 5,
      "energy": 25,
      "perks": {
        "forge": {
          "level": 3,
          "xp": 0
        },
        "combat": {
          "level": 1,
          "xp": 0,
          "bonus": 1
        }
      },
      "stats": {
        "attack": 3,
        "defence": 3,
        "speed": 0.1,
        "critic": 0.25
      }
    }
  }
}
